NexR_qc/ImageQC.py
NexR_qc/Logging.py
NexR_qc/QualityCheck.py
NexR_qc/StructedQC.py
NexR_qc/Timer.py
NexR_qc/__init__.py
NexR_qc/run.py
NexR_qc/utils/Logging.py
NexR_qc/utils/Timer.py
NexR_qc/utils/__init__.py
NexR_qc-0.0.13.dist-info/METADATA
NexR_qc-0.0.13.dist-info/WHEEL
NexR_qc-0.0.13.dist-info/top_level.txt
NexR_qc-0.0.13.dist-info/RECORD
